CHANGES.rst
MANIFEST.in
README.rst
setup.py
medeox_provider_client/Appointment.py
medeox_provider_client/MedeoxRestClient.py
medeox_provider_client/MedeoxSocketsClient.py
medeox_provider_client/Schedule.py
medeox_provider_client/Slot.py
medeox_provider_client/__init__.py
medeox_provider_client/exceptions.py
medeox_provider_client/utils.py
medeox_provider_client.egg-info/PKG-INFO
medeox_provider_client.egg-info/SOURCES.txt
medeox_provider_client.egg-info/dependency_links.txt
medeox_provider_client.egg-info/requires.txt
medeox_provider_client.egg-info/top_level.txt
medeox_provider_client.egg-info/zip-safe
medeox_provider_client/socketIO_client/__init__.py