Metadata-Version: 1.1
Name: medeox-provider-client
Version: 0.3
Summary: A Medeox provider client library
Home-page: https://github.com/medeox/Medeox.Provider.Python
Author: Medeox
Author-email: tech@doctoralia.com
License: TODO
Keywords: medeox websockets socket.io node.js
Platform: OS Independent
Classifier: Intended Audience :: Developers
Classifier: Programming Language :: Python
Classifier: Development Status :: 5 - Production/Stable
